{
  "meta": {
    "canonical": "https://raw.githubusercontent.com/jsonresume/resume-schema/master/schema.json",
    "version": "v1.0.0",
    "lastModified": "2020-08-06T20:00:00",
    "theme": "elegant"
  },
  "basics": {
    "name": "Tomasz Jaskiewicz",
    "label": "Senior Backend Software Engineer",
    "image": "https://secure.gravatar.com/avatar/acc4d22ff67c8bf3e033a0f2deefdca6",
    "summary": "I'm a backend software engineer with 6.5+ years' experience in Ruby, 3.5+ years' experience in Fintech industry (especially Cards industry). I'm a professional & skillful Rubyist, passionate about selfhosting, cloud and new technologies. An aspiring DevSecOps practitioner - I believe implementing DevSecOps philosophy makes outstanding projects. I have led multiple projects and teams. I'm looking for next challenge within a people-oriented, great culture, high-growth environment, remotely.",
    "website": "https://tjay.dev",
    "email": "contact@thomasjaskiewicz.com",
    "location": {
      "city": "Cracow",
      "countryCode": "PL",
      "region": "Lesser Poland"
    },
    "profiles": [
      {
        "username": "tomaszjaskiewicz",
        "url": "https://www.linkedin.com/in/tomaszjaskiewicz/",
        "network": "linkedin"
      },
      {
        "username": "tomjaskiewicz",
        "url": "https://twitter.com/tomjaskiewicz",
        "network": "twitter"
      },
      {
        "url": "https://github.com/tomajask/",
        "username": "tomajask",
        "network": "github"
      },
      {
        "url": "https://www.instagram.com/thomasjaskiewicz/",
        "username": "thomasjaskiewicz",
        "network": "instagram"
      },
      {
        "url": "https://dev.to/tjay_dev",
        "username": "tjay_dev",
        "network": "devto"
      }
    ]
  },
  "education": [
    {
      "institution": "AGH University of Science and Technology in Cracow",
      "url": "https://www.agh.edu.pl/en/",
      "area": "Computer Science",
      "studyType": "Engineer's degree",
      "startDate": "2010-12-31",
      "endDate": "2014-12-31",
      "courses": []
    },
    {
      "institution": "Tischner European University in Cracow",
      "url": "https://wse.krakow.pl/en/teu/",
      "area": "Managerial Studies",
      "studyType": "Postgraduate studies",
      "startDate": "2014-12-31",
      "endDate": "2015-12-31",
      "courses": []
    }
  ],
  "references": [
    {
      "name": "Maciej Pastuszka, Senior JavaScript Developer & Team Lead in SYZYGY, Warsaw",
      "reference": "As the project coordinator, Tomasz showed professionalism, he was able to skillfully plan activities that would translate into results and lead to the intended goal. In addition to team management skills, Tomasz showed knowledge in the field of IT. The combination of these skills contributed not only to the achievement of the goals of the project but also to the development of the members of which Tomasz was the coordinator."
    },
    {
      "name": "Michal Czyzewski, Data Scientist/Machine Learning Specialist",
      "reference": "Tomasz Jaskiewicz at work shows professionalism and professional curiosity. During the project, Tomasz constantly expanded his knowledge in its field, showed his own initiatives, and was heavily involved in the project."
    }
  ],
  "languages": [
    {
      "language": "Polish",
      "fluency": "Native Speaker"
    },
    {
      "language": "English",
      "fluency": "Professional working proficiency"
    }
  ],
  "skills": [
    {
      "name": "Software Development",
      "level": "",
      "keywords": [
        "HTML / CSS",
        "Javascript",
        "Object-Oriented Programming (OOP)",
        "Ruby / Ruby on Rails / Grape / Sidekiq / Shoryuken",
        "Git",
        "MySQL / PostgreSQL / NoSQL",
        "Software Architecture"
      ]
    },
    {
      "name": "Devops",
      "level": "",
      "keywords": [
        "Cloud Computing",
        "Ansible",
        "Docker",
        "Terraform",
        "Amazon Web Services / ECS / S3 / DynamoDB / Lambda / SQS / SNS / RDS / Cloudwatch",
        "Serverless",
        "Networking",
        "Infrastructure as Code"
      ]
    },
    {
      "name": "Marketing",
      "level": "",
      "keywords": [
        "Social Media Marketing",
        "Online Marketing",
        "Brand Management",
        "Email Marketing",
        "Marketing Strategy",
        "Web Analytics"
      ]
    },
    {
      "name": "Soft skills",
      "level": "",
      "keywords": [
        "Project Management",
        "Strategic Planning",
        "Team Leadership",
        "Team Management"
      ]
    }
  ],
  "awards": [],
  "certificates": [
    {
      "name": "AWS Certified Cloud Practitioner",
      "date": "2020-03-02",
      "url": "https://www.youracclaim.com/badges/9beeb356-d224-4516-8eaf-623c96ff0199/public_url",
      "issuer": "Amazon Web Services Training and Certification"
    },
    {
      "name": "Docker Fundamentals",
      "date": "2019-10-06",
      "url": "https://verify.acloud.guru/5308F78E8884",
      "issuer": "A Cloud Guru"
    }
  ],
  "work": [
    {
      "summary": "solarisBank builds and provides a Banking-as-a-Service platform for businesses based on various APIs. I joined Cards Team where from the beginning I worked on multiple cards related products, mainly in Ruby language.",
      "name": "solarisBank AG",
      "position": "Senior Backend Engineer",
      "startDate": "2017-10-04",
      "highlights": [
        "Cards Management - issuing and managing cards, integrating with 3rd party providers.",
        "Processing Cards Transactions - building a complex mechanism and service for processing card transactions.",
        "Smart Agent - allowing customers to receive and respond to fraud alerts digitally and moving fraud management away from labour-intensive call centers.",
        "3D Secure - an additional security layer for online credit and debit card transactions allowing our customers to be safer online.",
        "Cards Tokenization - tokenization of customers' cards allowing them to use digital wallets, like Apple, Google, Samsung.",
        "PCI DSS Compliance - building a safe and PCI DSS compliant security system for Cardholder Data (CHD) with Cyber & Architecture Teams.",
        "Building and moving to AWS infrastructure - designing and implementing infra as code for cards services during the company migration to AWS Cloud by leveraging Amazon Services for specific applications.",
        "Technologies: AWS: Fargate, S3, Lambda, RDS, DynamoDB, Secrets Manager, Cloudwatch, Terraform, Docker | Ruby: Sidekiq, Shoryuken, Grape, dry-rb, Sequel"
      ],
      "url": "https://www.solarisbank.com/en/"
    },
    {
      "summary": "2 projects: A LinkedIn-like platform for invitation-only users & An exclusive career marketplace that connects high-potential candidates to top-tier employers",
      "name": "Netguru",
      "position": "Senior Ruby on Rails Developer & Team Leader",
      "startDate": "2016-12-01",
      "endDate": "2020-01-31",
      "highlights": [
        "Functionality that enables user to add/remove job opportunity, to/from watching list, integrating application with Segment.io + implementing custom analytics events on backend, developing API for frontend part of the app, implementing a robust search engine with Searchkick and Elasticsearch, refactoring legacy code, implementing multiple user type architecture, implementing a CSV importer for adding new users to the platform, designing and implementing state machine structures for most common models, implementing referrals mechanism.",
        "Integrating new design with an already existing platform, setting up a staging environment and deployment with Capistrano, fixing bugs in frontend and backend part, speeding up an app by optimizing database queries, cleaning codebase by removing legacy code, implementing a panel to add career offers visible on a homepage, implementing a dashboard statistics panel to show users activity, fixing security issues, introducing decorators and service object patterns, implement tracking user activity services, introducing page objects pattern and implementing features specs."
      ],
      "url": "https://www.netguru.com/"
    },
    {
      "summary": "2 projects: A platform for job-seeking, recruitment, and learning for African market & An application for passive recruitment which uses external APIs to gather information about candidates and employers.",
      "name": "Netguru",
      "position": "Ruby on Rails Developer",
      "startDate": "2015-04-01",
      "endDate": "2016-12-01",
      "highlights": [
        "Email invitations secured with tokens, main functionalities in the platform like work experience references and skill references, campaign creation multistep form, a messaging system using Mailboxer gem, optimizing database queries to avoid performance issues.",
        "Designing and implementing main app's architecture, architecture for API clients, background processing solution using Sidekiq, simple event store solution for processing published events, a module for sending daily reports via email, panels for viewing/managing resources in an admin panel, monitoring for API queries in an admin panel, implementing a service to divide long titles into small meaningful keywords."
      ],
      "url": "https://www.netguru.com/"
    },
    {
      "summary": "2 projects: Flight support management app & Multi-platform where people can find each other quickly, conveniently and exchange services.",
      "name": "Netguru",
      "position": "Junior Ruby on Rails Developer",
      "startDate": "2015-01-01",
      "endDate": "2015-03-31",
      "highlights": [
        "Integrating the application with Amazon S3, improving new contacts addition and editing contacts details.",
        "Generating PDFs for vouchers and invoices, building validations for forms."
      ],
      "url": "https://www.netguru.com/"
    },
    {
      "summary": "One-month internship in the project building a video on demand platform.",
      "name": "Netguru",
      "position": "Ruby on Rails Intern",
      "startDate": "2014-12-01",
      "endDate": "2015-01-01",
      "highlights": [
        "Implementing discount coupons for purchase orders",
        "Sending emails to customers (overdue orders)"
      ],
      "url": "https://www.netguru.com/"
    },
    {
      "summary": "",
      "name": "AIESEC Krakow",
      "position": "Product Development Manager",
      "startDate": "2013-10-31",
      "endDate": "2015-03-31",
      "highlights": [],
      "url": "https://aiesec.pl/"
    },
    {
      "summary": "Interactive Agency founded in 2005 specialized in SEO, SEM, Social Media, creating Google Ads, Facebook Ads campaigns.",
      "name": "MTWeb.pl",
      "position": "e-Marketing Specialist",
      "startDate": "2014-06-30",
      "endDate": "2014-10-31",
      "highlights": [
        "Preparing email marketing campaigns & marketing strategies with advertising Campaigns in Adwords and FB Ads"
      ],
      "url": "https://mtweb.pl/"
    },
    {
      "summary": "",
      "name": "AIESEC Polska",
      "position": "Online Marketing Specialist",
      "startDate": "2014-02-28",
      "endDate": "2014-07-31",
      "highlights": [],
      "url": "https://aiesec.pl/"
    },
    {
      "summary": "",
      "name": "SALESmanago",
      "position": "Intern",
      "startDate": "2013-08-31",
      "endDate": "2013-11-30",
      "highlights": [],
      "url": "https://www.salesmanago.pl/"
    }
  ],
  "projects": [
    {
      "name": "Netguru College",
      "description": "Ruby on Rails Weekend Workshops | November Edition in Cracow",
      "highlights": [],
      "keywords": [
        "Ruby / Ruby on Rails"
      ],
      "startDate": "2018-11-03",
      "endDate": "2018-11-04",
      "roles": [
        "Mentor"
      ],
      "entity": "Netguru",
      "type": "workshops"
    },
    {
      "name": "Netguru College",
      "description": "Ruby on Rails Weekend Workshops | July Edition in Cracow",
      "highlights": [],
      "keywords": [
        "Ruby / Ruby on Rails"
      ],
      "startDate": "2018-07-07",
      "endDate": "2018-07-08",
      "roles": [
        "Mentor"
      ],
      "entity": "Netguru",
      "type": "workshops"
    },
    {
      "name": "Netguru Ruby on Rails Weekend Workshops",
      "description": "Ruby on Rails Weekend Workshops | December Edition in Katowice",
      "highlights": [],
      "keywords": [
        "Ruby / Ruby on Rails"
      ],
      "startDate": "2015-12-05",
      "endDate": "2015-12-06",
      "roles": [
        "Mentor"
      ],
      "entity": "Netguru",
      "type": "workshops"
    },
    {
      "name": "Netguru Ruby on Rails Weekend Workshops",
      "description": "Ruby on Rails Weekend Workshops | October Edition in Wroclaw",
      "highlights": [],
      "keywords": [
        "Ruby / Ruby on Rails"
      ],
      "startDate": "2015-10-03",
      "endDate": "2015-10-04",
      "roles": [
        "Mentor"
      ],
      "entity": "Netguru",
      "type": "workshops"
    }
  ],
  "volunteer": [],
  "publications": [
    {
      "name": "HowTo: My Terminal & Shell setup - Hyper.js + ZSH + starship",
      "publisher": "TJay.dev | Blog",
      "releaseDate": "2019-09-08",
      "url": "https://tjay.dev/howto-my-terminal-shell-setup-hyper-js-zsh-starship/",
      "summary": "How to configure terminal and shell to stay productive on a daily basis? Which shell to use? What are tips & tricks to speed up command line usage?"
    },
    {
      "name": "HowTo: Working efficiently with large files in Ruby",
      "publisher": "TJay.dev | Blog",
      "releaseDate": "2019-09-02",
      "url": "https://tjay.dev/howto-working-efficiently-with-large-files-in-ruby/",
      "summary": "How to process large files in Ruby while keeping CPU and memory usage in control?"
    },
    {
      "name": "Contributor in Ruby Weekly #292",
      "publisher": "Ruby Weekly",
      "releaseDate": "2019-09-02",
      "url": "https://rubyweekly.com/issues/292",
      "summary": "Picguard: Visual Identification for Filtering Purposes"
    }
  ],
  "interests": [
    {
      "name": "Sport",
      "keywords": [
        "Triathlon",
        "Cycling",
        "Running",
        "Swimming",
        "Bikepacking",
        "Crossfit",
        "Longboarding",
        "Yoga",
        "Kayaking",
        "Hiking"
      ]
    },
    {
      "name": "Gardening",
      "keywords": [
        "House plants",
        "Hydroponics",
        "Water plants",
        "Sustainability"
      ]
    },
    {
      "name": "Coffee",
      "keywords": [
        "Filter coffee",
        "Home Barista",
        "Speciality coffee"
      ]
    },
    {
      "name": "Selfhosting",
      "keywords": [
        "Open Source",
        "Home Automation",
        "Hosting services at home",
        "Smart Home",
        "New Technology"
      ]
    },
    {
      "name": "Travelling",
      "keywords": [
        "Food tourism",
        "Bikepacking",
        "Nature lover"
      ]
    }
  ]
}
